pop/__init__.py
pop/contract.py
pop/dirs.py
pop/exc.py
pop/hub.py
pop/loader.py
pop/scanner.py
pop/verify.py
pop/version.py
pop/mods/pop/conf.py
pop/mods/pop/config.py
pop/mods/pop/contract.py
pop/mods/pop/data.py
pop/mods/pop/dicts.py
pop/mods/pop/dyne.py
pop/mods/pop/input.py
pop/mods/pop/loop.py
pop/mods/pop/ref.py
pop/mods/pop/sub.py
pop/mods/pop/verify.py
pop-27.1.0.dist-info/LICENSE
pop-27.1.0.dist-info/METADATA
pop-27.1.0.dist-info/WHEEL
pop-27.1.0.dist-info/top_level.txt
pop-27.1.0.dist-info/RECORD
