Metadata-Version: 2.1
Name: pop
Version: 27.1.0
Summary: The Plugin Oriented Programming System
Home-page: https://pop.readthedocs.io
Author: Thomas S Hatch
Author-email: thatch@vmware.com
Classifier: Operating System :: OS Independent
Classifier: Programming Language :: Python :: 3.8
Classifier: Programming Language :: Python :: 3.9
Classifier: Programming Language :: Python :: 3.10
Classifier: Programming Language :: Python :: 3.11
Classifier: Programming Language :: Python :: 3.12
Classifier: Development Status :: 5 - Production/Stable
Requires-Python: >=3.8
License-File: LICENSE
Requires-Dist: dict-toolbox>=2.1.2
Requires-Dist: lazy_object_proxy
Requires-Dist: pop-config>=8.0.2
Requires-Dist: pop-loop<2.0.0,>=1.0.5
Requires-Dist: PyYAML>=6.0.1
